[
  {
    "title": "GAME SYMPHONY JAPAN 24th CONCERT KOEI TECMO Special　～シブサワ・コウ35周年記念～",
    "date": "Date not found",
    "venue": "Venue not found",
    "ticketUrl": null,
    "sourceUrl": "http://www.2083.jp/information/article_201709.html"
  },
  {
    "title": "PERSONA SUPER LIVE　P-SOUND BOMB!!!! 2017　～港の犯行を目撃せよ！～",
    "date": "Date not found",
    "venue": "Venue not found",
    "ticketUrl": null,
    "sourceUrl": "http://www.2083.jp/concert/20171123dq.html"
  },
  {
    "title": "NJBP Concert♯0“飛翔”",
    "date": "Date not found",
    "venue": "所沢市民文化センター ミューズ アークホール（大ホール）",
    "ticketUrl": "http://l-tike.com/bbj",
    "sourceUrl": "http://www.2083.jp/concert/20170923njbp.html"
  }
]